{
  "updated_at": "2026-07-10T17:48:37",
  "n_completed": 166,
  "n_failed": 0,
  "completed": [
    "BCNbanma",
    "BCNchenniningxi",
    "BCNdaodao",
    "BCNgaoqifana",
    "BCNgaoqifanb",
    "BCNgaoqifanc",
    "BCNgaoqifand",
    "BCNgaoqifane",
    "BCNgaoqifanf",
    "BCNgaoqifanv",
    "BCNqiaoba",
    "BCNqiaofeifei",
    "BCNqinwenjing",
    "BCNxiaomi",
    "BCNxieying0001",
    "BCNzhangxinfang",
    "BCNzhaoxi",
    "GSabaidu0001",
    "GSaierhaisen0001",
    "GSbabala0001",
    "GSbazyshenzi0001",
    "GSbeidou0001",
    "GSdadaliya",
    "GSdiona0001",
    "GSdixiya0001",
    "GSfalushan0001",
    "GSfengyuanwanye0001",
    "GSfuningna0001",
    "GShuanglongyidou0001",
    "GShutao0001",
    "GSkaiya0001",
    "GSkaqina0001",
    "GSkawei",
    "GSkelailei",
    "GSkeli0001",
    "GSkeqing0001",
    "GSkong0001",
    "GSlaila0001",
    "GSlaiousili0001",
    "GSleidianjiangjun0001",
    "GSlinni0001",
    "GSlisha",
    "GSluyeyuanpingcang0001",
    "GSmalani0001",
    "GSmaweika0001",
    "GSmengjianyueruixi0001",
    "GSmuna",
    "GSnaweilaite0001",
    "GSnaweiya0001",
    "GSnaxida0001",
    "GSnilu0001",
    "GSningguang",
    "GSnuoaier0001",
    "GSpaimeng",
    "GSsainuo0001",
    "GSshanhaigongxinhai",
    "GSshenlilinghua0001",
    "GStinab0001",
    "GStuomab0001",
    "GSwendidi",
    "GSxiangling0001",
    "GSxiaogong0001",
    "GSxinuoning0001",
    "GSxiterali",
    "GSyanfei0001",
    "GSyelan0001",
    "GSying0001",
    "GSzaoyou0001",
    "GSzhongli",
    "HKailixiya",
    "HKaiyinsitan",
    "HKaotuo",
    "HKbazy",
    "HKbulangni",
    "HKdibaliuzhe",
    "HKduya",
    "HKfuhua",
    "HKjizi",
    "HKkaiwen",
    "HKkalian",
    "HKkaluoer",
    "HKliliya",
    "HKlita",
    "HKtesila",
    "HKwaerte",
    "HKxier0001",
    "HKxier0002",
    "HKyiyi",
    "HKyoulandaier",
    "LAria",
    "Mieli",
    "SRageleya0001",
    "SRbaie",
    "SRbuluoniya",
    "SRdanhen",
    "SRfengjin0001",
    "SRfuxuan0001",
    "SRheitiane",
    "SRhuangquan0001",
    "SRjingyuan",
    "SRjizi0001",
    "SRkaitezhenv",
    "SRkaituozhe0001",
    "SRkelala0001",
    "SRliuying",
    "SRluke",
    "SRnakexia",
    "SRnatasha0001",
    "SRpeila",
    "SRsaifeier0001",
    "SRsanyueqi",
    "SRshajin",
    "SRwaerte",
    "SRwand",
    "SRxiadie0001",
    "SRxier",
    "SRxiluowa",
    "SRxingqiri0001",
    "SRyanqing0001",
    "SRyunli0001",
    "TTlujinghe",
    "TTmoyi",
    "TTxiayan",
    "TTxuyin",
    "TTzuoran",
    "WWanke0001",
    "WWbulante",
    "WWchangli",
    "WWchixia",
    "WWchun",
    "WWfeibi0001",
    "WWjinx0001",
    "WWjiyan",
    "WWkantelaila",
    "WWkelaite0001",
    "WWlingyang0001",
    "WWluokke",
    "WWpiaobozhenan",
    "WWpiaobozi",
    "WWqiushui",
    "WWshouanren0001",
    "WWxiangliyao",
    "WWyangyang",
    "WWyinlin",
    "WWzanini0001",
    "WWzhezhi0001",
    "Wumi",
    "Xiaoyuan",
    "Xuehusang",
    "乃琳",
    "云崎早_haya",
    "冥冥",
    "十六萤Izayoi",
    "叶绯页",
    "合成ria",
    "喵铃Neko",
    "嘉然",
    "塔神",
    "奈奈莉娅",
    "宣小纸不怕火",
    "晚晚sumi",
    "王宝煲",
    "皮皮",
    "礼墨",
    "花礼",
    "鸣海派"
  ],
  "failed": []
}